<?xml version="1.0" encoding="UTF-8"?> 
<java version="1.6.0_37" class="java.beans.XMLDecoder"> 
 <object class="WoWSerialization.WoWSerializationObjects.Implementation.WoWSerializableNode"> 
  <void property="description"> 
   <string>Send e-mail to desislava.stoyanova@asml.com with link to the created PDF and scheduled CCB.</string> 
  </void> 
  <void property="displayName"> 
   <string>Request project from SIMGT</string> 
  </void> 
  <void property="uniqueID"> 
   <string>req_proj_simgt</string> 
  </void> 
  <void property="taskDaysEstimate"> 
   <float>1</float> 
  </void>   
 </object> 
</java> 
